<annotation>
	<folder>image</folder>
	<filename>1207.jpg</filename>
	<path>C:\Users\Erin\Desktop\YYGdata2023.4.23\image\1207.jpg</path>
	<source>
		<database>Unknown</database>
	</source>
	<size>
		<width>1280</width>
		<height>1024</height>
		<depth>3</depth>
	</size>
	<segmented>0</segmented>
	<object>
		<name>ab</name>
		<pose>Unspecified</pose>
		<truncated>0</truncated>
		<difficult>0</difficult>
		<bndbox>
			<xmin>775</xmin>
			<ymin>417</ymin>
			<xmax>856</xmax>
			<ymax>499</ymax>
		</bndbox>
	</object>
	<object>
		<name>ab</name>
		<pose>Unspecified</pose>
		<truncated>0</truncated>
		<difficult>0</difficult>
		<bndbox>
			<xmin>806</xmin>
			<ymin>487</ymin>
			<xmax>888</xmax>
			<ymax>569</ymax>
		</bndbox>
	</object>
	<object>
		<name>ab</name>
		<pose>Unspecified</pose>
		<truncated>0</truncated>
		<difficult>0</difficult>
		<bndbox>
			<xmin>956</xmin>
			<ymin>480</ymin>
			<xmax>1044</xmax>
			<ymax>565</ymax>
		</bndbox>
	</object>
	<object>
		<name>ab</name>
		<pose>Unspecified</pose>
		<truncated>0</truncated>
		<difficult>0</difficult>
		<bndbox>
			<xmin>997</xmin>
			<ymin>434</ymin>
			<xmax>1065</xmax>
			<ymax>508</ymax>
		</bndbox>
	</object>
	<object>
		<name>ab</name>
		<pose>Unspecified</pose>
		<truncated>0</truncated>
		<difficult>0</difficult>
		<bndbox>
			<xmin>843</xmin>
			<ymin>333</ymin>
			<xmax>929</xmax>
			<ymax>420</ymax>
		</bndbox>
	</object>
	<object>
		<name>meso</name>
		<pose>Unspecified</pose>
		<truncated>0</truncated>
		<difficult>0</difficult>
		<bndbox>
			<xmin>779</xmin>
			<ymin>340</ymin>
			<xmax>853</xmax>
			<ymax>423</ymax>
		</bndbox>
	</object>
	<object>
		<name>ab</name>
		<pose>Unspecified</pose>
		<truncated>0</truncated>
		<difficult>0</difficult>
		<bndbox>
			<xmin>850</xmin>
			<ymin>431</ymin>
			<xmax>909</xmax>
			<ymax>492</ymax>
		</bndbox>
	</object>
</annotation>
