<annotation>
	<folder>image</folder>
	<filename>1727.jpg</filename>
	<path>C:\Users\Erin\Desktop\YYGdata2023.4.23\image\1727.jpg</path>
	<source>
		<database>Unknown</database>
	</source>
	<size>
		<width>1280</width>
		<height>1024</height>
		<depth>3</depth>
	</size>
	<segmented>0</segmented>
	<object>
		<name>ab</name>
		<pose>Unspecified</pose>
		<truncated>0</truncated>
		<difficult>0</difficult>
		<bndbox>
			<xmin>365</xmin>
			<ymin>166</ymin>
			<xmax>476</xmax>
			<ymax>274</ymax>
		</bndbox>
	</object>
	<object>
		<name>ab</name>
		<pose>Unspecified</pose>
		<truncated>0</truncated>
		<difficult>0</difficult>
		<bndbox>
			<xmin>514</xmin>
			<ymin>468</ymin>
			<xmax>590</xmax>
			<ymax>539</ymax>
		</bndbox>
	</object>
	<object>
		<name>ab</name>
		<pose>Unspecified</pose>
		<truncated>0</truncated>
		<difficult>0</difficult>
		<bndbox>
			<xmin>492</xmin>
			<ymin>208</ymin>
			<xmax>555</xmax>
			<ymax>279</ymax>
		</bndbox>
	</object>
	<object>
		<name>ab</name>
		<pose>Unspecified</pose>
		<truncated>0</truncated>
		<difficult>0</difficult>
		<bndbox>
			<xmin>550</xmin>
			<ymin>238</ymin>
			<xmax>667</xmax>
			<ymax>360</ymax>
		</bndbox>
	</object>
	<object>
		<name>histo</name>
		<pose>Unspecified</pose>
		<truncated>0</truncated>
		<difficult>0</difficult>
		<bndbox>
			<xmin>251</xmin>
			<ymin>375</ymin>
			<xmax>320</xmax>
			<ymax>456</ymax>
		</bndbox>
	</object>
	<object>
		<name>histo</name>
		<pose>Unspecified</pose>
		<truncated>0</truncated>
		<difficult>0</difficult>
		<bndbox>
			<xmin>915</xmin>
			<ymin>768</ymin>
			<xmax>986</xmax>
			<ymax>846</ymax>
		</bndbox>
	</object>
	<object>
		<name>ab</name>
		<pose>Unspecified</pose>
		<truncated>0</truncated>
		<difficult>0</difficult>
		<bndbox>
			<xmin>698</xmin>
			<ymin>76</ymin>
			<xmax>778</xmax>
			<ymax>160</ymax>
		</bndbox>
	</object>
	<object>
		<name>ab</name>
		<pose>Unspecified</pose>
		<truncated>0</truncated>
		<difficult>0</difficult>
		<bndbox>
			<xmin>888</xmin>
			<ymin>178</ymin>
			<xmax>941</xmax>
			<ymax>234</ymax>
		</bndbox>
	</object>
	<object>
		<name>ab</name>
		<pose>Unspecified</pose>
		<truncated>0</truncated>
		<difficult>0</difficult>
		<bndbox>
			<xmin>1034</xmin>
			<ymin>465</ymin>
			<xmax>1102</xmax>
			<ymax>538</ymax>
		</bndbox>
	</object>
	<object>
		<name>ab</name>
		<pose>Unspecified</pose>
		<truncated>0</truncated>
		<difficult>0</difficult>
		<bndbox>
			<xmin>1112</xmin>
			<ymin>401</ymin>
			<xmax>1192</xmax>
			<ymax>480</ymax>
		</bndbox>
	</object>
	<object>
		<name>ab</name>
		<pose>Unspecified</pose>
		<truncated>0</truncated>
		<difficult>0</difficult>
		<bndbox>
			<xmin>1120</xmin>
			<ymin>789</ymin>
			<xmax>1188</xmax>
			<ymax>861</ymax>
		</bndbox>
	</object>
	<object>
		<name>ab</name>
		<pose>Unspecified</pose>
		<truncated>0</truncated>
		<difficult>0</difficult>
		<bndbox>
			<xmin>1171</xmin>
			<ymin>861</ymin>
			<xmax>1232</xmax>
			<ymax>916</ymax>
		</bndbox>
	</object>
	<object>
		<name>meso</name>
		<pose>Unspecified</pose>
		<truncated>0</truncated>
		<difficult>0</difficult>
		<bndbox>
			<xmin>1101</xmin>
			<ymin>873</ymin>
			<xmax>1163</xmax>
			<ymax>932</ymax>
		</bndbox>
	</object>
	<object>
		<name>lymph</name>
		<pose>Unspecified</pose>
		<truncated>0</truncated>
		<difficult>0</difficult>
		<bndbox>
			<xmin>906</xmin>
			<ymin>978</ymin>
			<xmax>942</xmax>
			<ymax>1015</ymax>
		</bndbox>
	</object>
	<object>
		<name>lymph</name>
		<pose>Unspecified</pose>
		<truncated>0</truncated>
		<difficult>0</difficult>
		<bndbox>
			<xmin>1025</xmin>
			<ymin>687</ymin>
			<xmax>1058</xmax>
			<ymax>725</ymax>
		</bndbox>
	</object>
	<object>
		<name>ab</name>
		<pose>Unspecified</pose>
		<truncated>0</truncated>
		<difficult>0</difficult>
		<bndbox>
			<xmin>764</xmin>
			<ymin>818</ymin>
			<xmax>812</xmax>
			<ymax>876</ymax>
		</bndbox>
	</object>
	<object>
		<name>ab</name>
		<pose>Unspecified</pose>
		<truncated>0</truncated>
		<difficult>0</difficult>
		<bndbox>
			<xmin>921</xmin>
			<ymin>527</ymin>
			<xmax>991</xmax>
			<ymax>610</ymax>
		</bndbox>
	</object>
</annotation>
