<annotation>
	<folder>images</folder>
	<filename>288.jpg</filename>
	<path>C:\Users\Erin\Desktop\肺癌数据\images\288.jpg</path>
	<source>
		<database>Unknown</database>
	</source>
	<size>
		<width>1280</width>
		<height>1024</height>
		<depth>3</depth>
	</size>
	<segmented>0</segmented>
	<object>
		<name>meso</name>
		<pose>Unspecified</pose>
		<truncated>0</truncated>
		<difficult>0</difficult>
		<bndbox>
			<xmin>710</xmin>
			<ymin>471</ymin>
			<xmax>781</xmax>
			<ymax>547</ymax>
		</bndbox>
	</object>
	<object>
		<name>lymph</name>
		<pose>Unspecified</pose>
		<truncated>0</truncated>
		<difficult>0</difficult>
		<bndbox>
			<xmin>475</xmin>
			<ymin>658</ymin>
			<xmax>509</xmax>
			<ymax>696</ymax>
		</bndbox>
	</object>
	<object>
		<name>lymph</name>
		<pose>Unspecified</pose>
		<truncated>0</truncated>
		<difficult>0</difficult>
		<bndbox>
			<xmin>365</xmin>
			<ymin>320</ymin>
			<xmax>400</xmax>
			<ymax>359</ymax>
		</bndbox>
	</object>
	<object>
		<name>lymph</name>
		<pose>Unspecified</pose>
		<truncated>0</truncated>
		<difficult>0</difficult>
		<bndbox>
			<xmin>827</xmin>
			<ymin>889</ymin>
			<xmax>865</xmax>
			<ymax>930</ymax>
		</bndbox>
	</object>
	<object>
		<name>lymph</name>
		<pose>Unspecified</pose>
		<truncated>0</truncated>
		<difficult>0</difficult>
		<bndbox>
			<xmin>612</xmin>
			<ymin>979</ymin>
			<xmax>649</xmax>
			<ymax>1017</ymax>
		</bndbox>
	</object>
	<object>
		<name>lymph</name>
		<pose>Unspecified</pose>
		<truncated>0</truncated>
		<difficult>0</difficult>
		<bndbox>
			<xmin>694</xmin>
			<ymin>359</ymin>
			<xmax>730</xmax>
			<ymax>392</ymax>
		</bndbox>
	</object>
	<object>
		<name>lymph</name>
		<pose>Unspecified</pose>
		<truncated>0</truncated>
		<difficult>0</difficult>
		<bndbox>
			<xmin>800</xmin>
			<ymin>474</ymin>
			<xmax>840</xmax>
			<ymax>509</ymax>
		</bndbox>
	</object>
	<object>
		<name>lymph</name>
		<pose>Unspecified</pose>
		<truncated>0</truncated>
		<difficult>0</difficult>
		<bndbox>
			<xmin>799</xmin>
			<ymin>508</ymin>
			<xmax>839</xmax>
			<ymax>551</ymax>
		</bndbox>
	</object>
	<object>
		<name>lymph</name>
		<pose>Unspecified</pose>
		<truncated>0</truncated>
		<difficult>0</difficult>
		<bndbox>
			<xmin>208</xmin>
			<ymin>739</ymin>
			<xmax>241</xmax>
			<ymax>778</ymax>
		</bndbox>
	</object>
	<object>
		<name>lymph</name>
		<pose>Unspecified</pose>
		<truncated>0</truncated>
		<difficult>0</difficult>
		<bndbox>
			<xmin>776</xmin>
			<ymin>576</ymin>
			<xmax>815</xmax>
			<ymax>606</ymax>
		</bndbox>
	</object>
</annotation>
