<annotation>
	<folder>image</folder>
	<filename>353.jpg</filename>
	<path>C:\Users\Erin\Desktop\YYGdata2023.4.23\image\353.jpg</path>
	<source>
		<database>Unknown</database>
	</source>
	<size>
		<width>1280</width>
		<height>1024</height>
		<depth>3</depth>
	</size>
	<segmented>0</segmented>
	<object>
		<name>ab</name>
		<pose>Unspecified</pose>
		<truncated>0</truncated>
		<difficult>0</difficult>
		<bndbox>
			<xmin>877</xmin>
			<ymin>805</ymin>
			<xmax>928</xmax>
			<ymax>856</ymax>
		</bndbox>
	</object>
	<object>
		<name>lymph</name>
		<pose>Unspecified</pose>
		<truncated>0</truncated>
		<difficult>0</difficult>
		<bndbox>
			<xmin>1165</xmin>
			<ymin>688</ymin>
			<xmax>1230</xmax>
			<ymax>746</ymax>
		</bndbox>
	</object>
	<object>
		<name>lymph</name>
		<pose>Unspecified</pose>
		<truncated>0</truncated>
		<difficult>0</difficult>
		<bndbox>
			<xmin>50</xmin>
			<ymin>194</ymin>
			<xmax>98</xmax>
			<ymax>242</ymax>
		</bndbox>
	</object>
	<object>
		<name>lymph</name>
		<pose>Unspecified</pose>
		<truncated>0</truncated>
		<difficult>0</difficult>
		<bndbox>
			<xmin>999</xmin>
			<ymin>599</ymin>
			<xmax>1049</xmax>
			<ymax>642</ymax>
		</bndbox>
	</object>
	<object>
		<name>lymph</name>
		<pose>Unspecified</pose>
		<truncated>0</truncated>
		<difficult>0</difficult>
		<bndbox>
			<xmin>865</xmin>
			<ymin>870</ymin>
			<xmax>905</xmax>
			<ymax>915</ymax>
		</bndbox>
	</object>
	<object>
		<name>lymph</name>
		<pose>Unspecified</pose>
		<truncated>0</truncated>
		<difficult>0</difficult>
		<bndbox>
			<xmin>251</xmin>
			<ymin>622</ymin>
			<xmax>291</xmax>
			<ymax>666</ymax>
		</bndbox>
	</object>
	<object>
		<name>lymph</name>
		<pose>Unspecified</pose>
		<truncated>0</truncated>
		<difficult>0</difficult>
		<bndbox>
			<xmin>259</xmin>
			<ymin>175</ymin>
			<xmax>305</xmax>
			<ymax>226</ymax>
		</bndbox>
	</object>
	<object>
		<name>lymph</name>
		<pose>Unspecified</pose>
		<truncated>0</truncated>
		<difficult>0</difficult>
		<bndbox>
			<xmin>576</xmin>
			<ymin>686</ymin>
			<xmax>621</xmax>
			<ymax>734</ymax>
		</bndbox>
	</object>
</annotation>
